{
  "proposalId": "proposal_1774862517863",
  "proposalName": "test 5",
  "clientName": "",
  "notes": "",
  "createdBy": {
    "email": "jacktong@simplesymbol.com",
    "name": "jacktong"
  },
  "createdAt": "2026-03-30T09:21:58.162Z",
  "updatedAt": "2026-03-30T09:37:02.694Z",
  "products": [
    {
      "id": "taobao_744082767362",
      "source_id": "744082767362",
      "source": "taobao",
      "title": "Colorful mini candy simulation rainbow candy miniature food toy candy handmade DIY cream glue phone case nail accessories",
      "price": {
        "current": 7.09,
        "currency": "CNY",
        "original": 7.09
      },
      "image_urls": [
        "https://img.alicdn.com/imgextra/i2/736590379/O1CN01GadRuB1EfczyIByB9_!!736590379.jpg"
      ],
      "url": "https://item.taobao.com/item.htm?id=744082767362",
      "seller": {
        "name": "Unknown",
        "id": null,
        "rating": null,
        "location": ""
      }
    }
  ],
  "itemDetails": {
    "744082767362": {
      "title": "Colorful mini candy simulation rainbow candy miniature food toy candy handmade DIY cream glue phone case nail accessories",
      "desc_short": "",
      "brand": "Xiao Aijia",
      "pic_url": "//img.alicdn.com/imgextra/i2/736590379/O1CN01GadRuB1EfczyIByB9_!!736590379.jpg",
      "item_imgs": [
        {
          "url": "//img.alicdn.com/imgextra/i2/736590379/O1CN01GadRuB1EfczyIByB9_!!736590379.jpg"
        },
        {
          "url": "//img.alicdn.com/imgextra/i3/736590379/O1CN01hTkKhE1Efczw1Mb3I_!!736590379.jpg"
        },
        {
          "url": "//img.alicdn.com/imgextra/i4/736590379/O1CN018UHbdE1EfczkXwb7O_!!736590379.jpg"
        },
        {
          "url": "//img.alicdn.com/imgextra/i1/736590379/O1CN01VqSl1V1EfcztwBmcz_!!736590379.jpg"
        },
        {
          "url": "//img.alicdn.com/imgextra/i3/736590379/O1CN01IVNl9F1EfczssUKbh_!!736590379.jpg"
        }
      ],
      "prop_imgs": {
        "prop_img": [
          {
            "properties": "1627207:32631086117",
            "url": "http://img.alicdn.com/imgextra/i4/736590379/O1CN019GqFeG1EfczpCI0uD_!!736590379.jpg"
          },
          {
            "properties": "1627207:32631086118",
            "url": "http://img.alicdn.com/imgextra/i1/736590379/O1CN01bDeFT31Efczz5Eh59_!!736590379.jpg"
          },
          {
            "properties": "1627207:32631086119",
            "url": "http://img.alicdn.com/imgextra/i2/736590379/O1CN01SHiqZ41EfczqvNHIy_!!736590379.jpg"
          },
          {
            "properties": "1627207:32631086120",
            "url": "http://img.alicdn.com/imgextra/i3/736590379/O1CN01Tb5lun1Efd4GxOZhK_!!736590379.jpg"
          },
          {
            "properties": "1627207:32631086121",
            "url": "http://img.alicdn.com/imgextra/i2/736590379/O1CN01E2Cc3t1Efd4HEzVL9_!!736590379.jpg"
          },
          {
            "properties": "1627207:32631086122",
            "url": "http://img.alicdn.com/imgextra/i3/736590379/O1CN01CryBk81Efd4K7Q4wl_!!736590379.jpg"
          }
        ]
      },
      "props": [
        {
          "name": "Brand",
          "value": "Xiao Ai's family",
          "name_original": "Brand",
          "value_original": "Xiao Ai's family"
        },
        {
          "name": "Item number",
          "value": "075461",
          "name_original": "Item number",
          "value_original": "075461"
        },
        {
          "name": "Place of Origin",
          "value": "Chinese Mainland",
          "name_original": "Place of Origin",
          "value_original": "Chinese Mainland"
        },
        {
          "name": "province",
          "value": "Guangdong Province",
          "name_original": "province",
          "value_original": "Guangdong Province"
        },
        {
          "name": "region",
          "value": "Shanwei City",
          "name_original": "region",
          "value_original": "Shanwei City"
        },
        {
          "name": "quantity",
          "value": "50",
          "name_original": "quantity",
          "value_original": "50"
        },
        {
          "name": "Color classification",
          "value": "10 simulated mini 6mm lollipops, 50 simulated mini 6mm lollipops, 100 simulated mini 6mm lollipops, 10 simulated mini 4mm lollipops, 50 simulated mini 4mm lollipops, and 100 simulated mini 4mm lollipops",
          "name_original": "Color classification",
          "value_original": "10 simulated mini 6mm lollipops, 50 simulated mini 6mm lollipops, 100 simulated mini 6mm lollipops, 10 simulated mini 4mm lollipops, 50 simulated mini 4mm lollipops, and 100 simulated mini 4mm lollipops"
        }
      ],
      "moq": 1,
      "category_id": "50021930",
      "category": "DIY simulation materials",
      "fav_count": null,
      "fans_count": null,
      "created_time": "",
      "rating_grade": null,
      "seller": {
        "name": "Xiao Aijia supply chain",
        "location": "Guangdong Shanwei",
        "rating": null,
        "name_original": "小艾家供应链",
        "location_original": "广东汕尾"
      },
      "sales_volume": 1000,
      "description": "100.0%;\" src=\"https://img.alicdn.com/imgextra/i1/736590379/O1CN01gWuhfd1Efczsw72EF_!!736590379.jpg\"><img style=\"display: block;width: 100.0%;\" src=\"https://img.alicdn.com/imgextra/i2/736590379/O1CN01AQR5fu1EfcztwAyuK_!!736590379.jpg\"><img style=\"display: block;width: 100.0%;\" src=\"https://img.alicdn.com/imgextra/i3/736590379/O1CN01hAhF3B1EfczvgMrA0_!!736590379.jpg\"><img style=\"display: block;width: 100.0%;\" src=\"https://img.alicdn.com/imgextra/i3/736590379/O1CN01PzWWS71EfczpC68NJ_!!736590379.jpg\"><img style=\"display: block;width: 100.0%;\" src=\"https://img.alicdn.com/imgextra/i2/736590379/O1CN015zZLh61EfczvgPoG0_!!736590379.jpg\"></div></div>",
      "title_original": "Colorful mini candy simulation rainbow candy miniature food toy candy handmade DIY cream glue phone case nail accessories",
      "description_original": "<div style=\"width: 750.0px;height: 3408.0px;overflow: hidden;\"><div style=\"width: 750.0px;height: 3408.0px;overflow: hidden;\"><img style=\"display: block;width: 100.0%;\" src=\"https://img.alicdn.com/imgextra/i1/736590379/O1CN01gWuhfd1Efczsw72EF_!!736590379.jpg\"><img style=\"display: block;width: 100.0%;\" src=\"https://img.alicdn.com/imgextra/i2/736590379/O1CN01AQR5fu1EfcztwAyuK_!!736590379.jpg\"><img style=\"display: block;width: 100.0%;\" src=\"https://img.alicdn.com/imgextra/i3/736590379/O1CN01hAhF3B1EfczvgMrA0_!!736590379.jpg\"><img style=\"display: block;width: 100.0%;\" src=\"https://img.alicdn.com/imgextra/i3/736590379/O1CN01PzWWS71EfczpC68NJ_!!736590379.jpg\"><img style=\"display: block;width: 100.0%;\" src=\"https://img.alicdn.com/imgextra/i2/736590379/O1CN015zZLh61EfczvgPoG0_!!736590379.jpg\"></div></div>",
      "brand_original": "小艾家",
      "category_original": "DIY仿真材料",
      "productId": "744082767362",
      "platform": "taobao",
      "fetchedAt": "2026-03-30T09:22:04.669Z",
      "selectedSecondaryImages": [
        "https://img.alicdn.com/imgextra/i2/736590379/O1CN01GadRuB1EfczyIByB9_!!736590379.jpg",
        "https://img.alicdn.com/imgextra/i3/736590379/O1CN01hTkKhE1Efczw1Mb3I_!!736590379.jpg",
        "https://img.alicdn.com/imgextra/i4/736590379/O1CN018UHbdE1EfczkXwb7O_!!736590379.jpg",
        "https://img.alicdn.com/imgextra/i1/736590379/O1CN01VqSl1V1EfcztwBmcz_!!736590379.jpg"
      ],
      "selectedAIImages": [
        "/ai-images/proposal_1774862517863/744082767362/concept-0.png",
        "/ai-images/proposal_1774862517863/744082767362/concept-1.png",
        "/ai-images/proposal_1774862517863/744082767362/concept-2.png",
        "/ai-images/proposal_1774862517863/744082767362/concept-3.png"
      ]
    }
  },
  "totalItems": 1,
  "successfulItems": 1,
  "aiEnrichments": {
    "744082767362": {
      "original_product": {
        "title": "Rainbow Lollipop Craft Charms",
        "description": "Assorted miniature striped lollipop-shaped plastic charms for DIY crafts and jewelry making.",
        "specifications": {
          "dimensions": "Approx. 1.2 x 0.8 cm (0.5 x 0.3 inches) per charm",
          "weight": "N/A (very light, likely <1g per piece)",
          "materials": "Translucent resin or acrylic plastic",
          "other_specs": "Small loop/hole for attachment, striped pattern"
        }
      },
      "design_alternatives": [
        {
          "concept_title": "Sweet Treat Push Pins",
          "generated_image_prompt": "A set of colorful, miniature, lollipop-shaped push pins with white plastic sticks and sharp metal points. The lollipop heads feature vibrant rainbow stripes and solid colors, made from translucent resin. They are neatly arranged on a corkboard, casting soft shadows. Studio lighting, bright and playful, close up shot.",
          "short_description": "Adorable lollipop push pins for corkboards and decorative organization.",
          "design_rationale": "Transforms the decorative charm into a functional office or home accessory. Retains the playful aesthetic while adding practical utility, appealing to stationery enthusiasts and gift buyers. Easy to manufacture by combining existing charm molds with standard push pin components.",
          "generated_image_url": "/ai-images/proposal_1774862517863/744082767362/concept-0.png"
        },
        {
          "concept_title": "Kawaii Dessert Keychains",
          "generated_image_prompt": "A collection of small, stylized keychains in the shapes of miniature desserts: a cupcake with sprinkles, an ice cream cone, a donut, and a macaron. Made from opaque, pastel-colored soft PVC or silicone, with a matte finish. Each has a small silver metal keyring attached. Clean studio shot, soft lighting, slightly elevated angle.",
          "short_description": "Cute, soft dessert-themed keychains for bags and keys.",
          "design_rationale": "Broadens the 'sweet treat' theme to popular dessert icons, utilizing a soft, durable material like PVC or silicone for a tactile and long-lasting product. High gifting appeal due to the universally loved 'kawaii' aesthetic and practical use as a keychain or bag charm.",
          "generated_image_url": "/ai-images/proposal_1774862517863/744082767362/concept-1.png"
        },
        {
          "concept_title": "Abstract Candy Coasters",
          "generated_image_prompt": "A set of four modern, minimalist coasters, each shaped like a smooth, rounded, slightly irregular 'candy drop.' They are made from solid, matte-finish silicone in muted pastel colors (blush pink, mint green, sky blue, lavender). The edges are soft and organic. Photographed from above on a light wooden table, with a ceramic mug resting on one coaster, subtle texture.",
          "short_description": "Stylish, non-slip coasters with a subtle, abstract candy shape.",
          "design_rationale": "Elevates the 'candy' inspiration into a sophisticated home decor item. The abstract, organic shape and matte silicone material offer a contemporary, understated aesthetic, appealing to a more mature audience seeking subtle whimsy in their functional items. Silicone is durable, easy to clean, and manufacturable via molding.",
          "generated_image_url": "/ai-images/proposal_1774862517863/744082767362/concept-2.png"
        },
        {
          "concept_title": "Stackable Candy Blocks",
          "generated_image_prompt": "A set of brightly colored, interlocking building blocks shaped like segmented candies or oversized gumballs. Each block has a flat top and bottom with interlocking studs/holes, similar to popular construction toys. Made from durable, opaque ABS plastic in primary and secondary colors (red, blue, yellow, green, orange, purple). They are stacked in playful, architectural arrangements on a clean white background, studio lighting.",
          "short_description": "Fun, colorful interlocking blocks for creative play and decoration.",
          "design_rationale": "Transforms the candy aesthetic into an interactive toy or desk accessory. The modular, interlocking design encourages creative play and repeated engagement, appealing to children and adults alike. ABS plastic is a standard, robust material for such toys, ensuring durability and manufacturability at scale.",
          "generated_image_url": "/ai-images/proposal_1774862517863/744082767362/concept-3.png"
        }
      ],
      "enriched_at": "2026-03-30T09:36:31.003Z"
    }
  }
}